LICENSE
README.md
pyproject.toml
setup.py
src/opencp/__init__.py
src/opencp/queue.py
src/opencp.egg-info/PKG-INFO
src/opencp.egg-info/SOURCES.txt
src/opencp.egg-info/dependency_links.txt
src/opencp.egg-info/top_level.txt
src/opencp/backend/c_queue.c
tests/test_queue.py