Metadata-Version: 2.4
Name: opencp
Version: 0.0.1
Summary: High-performance data structures for Competitive Programming
Author-email: Andreas <andreas@example.com>
License: MIT License
Classifier: Development Status :: 2 - Pre-Alpha
Requires-Python: >=3.8
License-File: LICENSE
Dynamic: license-file
